setup.py
protopigeon/__init__.py
protopigeon/converters.py
protopigeon/translators.py
protopigeon/types.py
protopigeon.egg-info/PKG-INFO
protopigeon.egg-info/SOURCES.txt
protopigeon.egg-info/dependency_links.txt
protopigeon.egg-info/top_level.txt