Metadata-Version: 1.1
Name: protopigeon
Version: 1.0.0
Summary: A helper library for working with Google's protorpc and App Engine's datastore
Home-page: https://bitbucket.org/jonparrott/protopigeon
Author: Jon Parrott / Cloud Sherpas
Author-email: jonathan.parrott@cloudsherpas.com
License: Apache License 2.0
Platform: UNKNOWN
Classifier: Development Status :: 5 - Production/Stable
Classifier: License :: OSI Approved :: Apache Software License
Classifier: Programming Language :: Python
